{
    "metaInfo": {
        "dataIndex": "config",
        "collectionName": "configObjects",
        "responseObjectName": "response"
    },
    "configObjects": [
        {
            "id": "rock-entity-create_exlieferantenartikel_uiConfig",
            "name": "rock-entity-create_exlieferantenartikel",
            "type": "uiConfig",
            "properties": {
                "createdService": "configurationManageService",
                "createdBy": "rewe.admin@riversand.com_user",
                "modifiedService": "configurationManageService",
                "modifiedBy": "rewe.admin@riversand.com_user",
                "createdDate": "2021-09-07T08:46:23.483-0500",
                "modifiedDate": "2021-09-07T08:46:23.483-0500"
            },
            "data": {
                "contexts": [
                    {
                        "context": {
                           
                            "component": "rock-entity-create",
                            "entityType": "exlieferantenartikel"
                        },
                        "jsonData": {
                            "config": {
                                "properties": {
                                    "attributeNames": [
                                        "axartikelkurztext"
                                    ]
                                }
                            }
                        }
                    }
                ]
            }
        }
    ]
}